pykern/__init__.py
pykern/fconf.py
pykern/mpi.py
pykern/pkarray.py
pykern/pkasyncio.py
pykern/pkcollections.py
pykern/pkcompat.py
pykern/pkconfig.py
pykern/pkconst.py
pykern/pkdebug.py
pykern/pkexample.py
pykern/pkinspect.py
pykern/pkio.py
pykern/pkjinja.py
pykern/pkjson.py
pykern/pkplatform.py
pykern/pkresource.py
pykern/pkrunpy.py
pykern/pksetup.py
pykern/pksubprocess.py
pykern/pkunit.py
pykern/pkyaml.py
pykern/pykern_console.py
pykern/pytest_plugin.py
pykern/quest.py
pykern/sql_db.py
pykern/util.py
pykern/xlsx.py
pykern/api/__init__.py
pykern/api/auth_api.py
pykern/api/client.py
pykern/api/server.py
pykern/api/unit_util.py
pykern/api/util.py
pykern/package_data/sphinx-conf.py
pykern/package_data/test.yml
pykern/package_data/projex/README.md.jinja
pykern/package_data/projex/dot-gitignore.jinja
pykern/package_data/projex/dot-readthedocs.yml.jinja
pykern/package_data/projex/pyproject.toml.jinja
pykern/package_data/projex/.github/workflows/python-ci.yml.jinja
pykern/package_data/projex/docs/dot-gitignore.jinja
pykern/package_data/projex/docs/index.rst.jinja
pykern/package_data/projex/docs/_static/dot-gitignore.jinja
pykern/package_data/projex/docs/_templates/dot-gitignore.jinja
pykern/package_data/projex/projex/__init__.py.jinja
pykern/package_data/projex/projex/projex_console.py.jinja
pykern/package_data/projex/projex/package_data/dot-gitignore.jinja
pykern/package_data/projex/projex/pkcli/__init__.py.jinja
pykern/package_data/projex/tests/dot-gitignore.jinja
pykern/package_data/projex/tests/import_test.py.jinja
pykern/package_data/projex-licenses/agpl-3.0.txt
pykern/package_data/projex-licenses/apache2.jinja
pykern/package_data/projex-licenses/gpl2.jinja
pykern/package_data/projex-licenses/gpl3.jinja
pykern/package_data/projex-licenses/lgpl2.jinja
pykern/package_data/projex-licenses/lgpl3.jinja
pykern/package_data/projex-licenses/mit.jinja
pykern/package_data/projex-licenses/proprietary.jinja
pykern/pkcli/__init__.py
pykern/pkcli/ci.py
pykern/pkcli/fmt.py
pykern-20250917.184614.dist-info/licenses/LICENSE
pykern-20250917.184614.dist-info/METADATA
pykern-20250917.184614.dist-info/WHEEL
pykern-20250917.184614.dist-info/entry_points.txt
pykern-20250917.184614.dist-info/top_level.txt
pykern-20250917.184614.dist-info/RECORD
